colabrsync/__init__.py
colabrsync/rsyncmirror.py
colabrsync-0.2.0.dist-info/LICENSE
colabrsync-0.2.0.dist-info/WHEEL
colabrsync-0.2.0.dist-info/METADATA
colabrsync-0.2.0.dist-info/RECORD
